docstr_md/__init__.py
docstr_md/python/__init__.py
docstr_md/python/soup_objects.py
docstr_md/python/compilers/__init__.py
docstr_md/python/compilers/sklearn.py
docstr_md/python/compilers/sklearn_templates/field.html
docstr_md/python/compilers/sklearn_templates/head.html
docstr_md/python/compilers/sklearn_templates/header.html
docstr_md/python/compilers/sklearn_templates/item.html
docstr_md/python/compilers/sklearn_templates/src_href.html
docstr_md/python/compilers/sklearn_templates/table.html
docstr_md/python/parsers/__init__.py
docstr_md/python/parsers/sklearn.py
docstr_md/src_href/__init__.py
docstr_md/src_href/github.py
docstr_md-0.0.9.dist-info/LICENSE
docstr_md-0.0.9.dist-info/METADATA
docstr_md-0.0.9.dist-info/WHEEL
docstr_md-0.0.9.dist-info/top_level.txt
docstr_md-0.0.9.dist-info/RECORD
