Metadata-Version: 2.1
Name: docstr-md
Version: 0.0.9
Summary: A fast and easy way to make beautiful documentation markdown files.
Home-page: https://dsbowen.github.io/docstr-md
Author: Dillon Bowen
Author-email: dsbowen@wharton.upenn.edu
License: UNKNOWN
Platform: UNKNOWN
Classifier: Programming Language :: Python :: 3
Classifier: License :: OSI Approved :: MIT License
Classifier: Operating System :: OS Independent
Requires-Python: >=3.6
Requires-Dist: astor (>=0.8.1)
Requires-Dist: pathlib (>=1.0.1)
